apex/__init__.py
apex/__main__.py
apex/archive.py
apex/config.py
apex/flow.py
apex/main.py
apex/report.py
apex/step.py
apex/submit.py
apex/utils.py
apex/core/__init__.py
apex/core/common_equi.py
apex/core/common_prop.py
apex/core/constants.py
apex/core/gen_confs.py
apex/core/mpdb.py
apex/core/refine.py
apex/core/reproduce.py
apex/core/structure.py
apex/core/calculator/ABACUS.py
apex/core/calculator/Lammps.py
apex/core/calculator/Task.py
apex/core/calculator/VASP.py
apex/core/calculator/__init__.py
apex/core/calculator/calculator.py
apex/core/calculator/lib/__init__.py
apex/core/calculator/lib/abacus_scf.py
apex/core/calculator/lib/abacus_utils.py
apex/core/calculator/lib/lammps_utils.py
apex/core/calculator/lib/vasp_utils.py
apex/core/lib/__init__.py
apex/core/lib/crys.py
apex/core/lib/dispatcher.py
apex/core/lib/lmp.py
apex/core/lib/mfp_eosfit.py
apex/core/lib/pwscf.py
apex/core/lib/siesta.py
apex/core/lib/slab_orientation.py
apex/core/lib/trans_tools.py
apex/core/lib/util.py
apex/core/lib/utils.py
apex/core/property/EOS.py
apex/core/property/Elastic.py
apex/core/property/Gamma.py
apex/core/property/Interstitial.py
apex/core/property/Phonon.py
apex/core/property/Property.py
apex/core/property/Surface.py
apex/core/property/Vacancy.py
apex/core/property/__init__.py
apex/database/DatabaseFactory.py
apex/database/DynamoDB.py
apex/database/MongoDB.py
apex/database/StorageBase.py
apex/database/__init__.py
apex/op/RunLAMMPS.py
apex/op/__init__.py
apex/op/property_ops.py
apex/op/relaxation_ops.py
apex/reporter/DashReportApp.py
apex/reporter/__init__.py
apex/reporter/property_report.py
apex/reporter/relaxation_report.py
apex/superop/RelaxationFlow.py
apex/superop/SimplePropertySteps.py
apex/superop/__init__.py
apex_flow-1.2.18.dist-info/licenses/LICENSE
tests/__init__.py
tests/context.py
tests/test_abacus.py
tests/test_abacus_equi.py
tests/test_abacus_property.py
tests/test_elastic.py
tests/test_eos.py
tests/test_gamma.py
tests/test_interstitial.py
tests/test_lammps.py
tests/test_make_prop.py
tests/test_mpdb.py
apex_flow-1.2.18.dist-info/METADATA
apex_flow-1.2.18.dist-info/WHEEL
apex_flow-1.2.18.dist-info/entry_points.txt
apex_flow-1.2.18.dist-info/top_level.txt
apex_flow-1.2.18.dist-info/RECORD
