Metadata-Version: 2.4
Name: apex-flow
Version: 1.2.18
Summary: Alloy Properties EXplorer using simulations
Home-page: https://github.com/deepmodeling/APEX.git
Author: Zhuoyuan Li, Tongqi Wen
Author-email: zhuoyli@outlook.com
Classifier: Programming Language :: Python :: 3
Classifier: License :: OSI Approved :: GNU Lesser General Public License v3 (LGPLv3)
Classifier: Operating System :: OS Independent
Requires-Python: >=3.10
License-File: LICENSE
Requires-Dist: numpy<2.0.0
Requires-Dist: pydflow>=1.7.83
Requires-Dist: pymatgen>=2023.8.10
Requires-Dist: pymatgen-analysis-defects>=2023.8.22
Requires-Dist: dpdata==0.2.17
Requires-Dist: dpdispatcher
Requires-Dist: phonopy
Requires-Dist: plotly
Requires-Dist: dash
Requires-Dist: dash_bootstrap_components
Requires-Dist: seekpath
Requires-Dist: fpop>=0.0.7
Requires-Dist: boto3
Requires-Dist: pymongo
Dynamic: author
Dynamic: author-email
Dynamic: classifier
Dynamic: description
Dynamic: description-content-type
Dynamic: home-page
Dynamic: license-file
Dynamic: requires-dist
Dynamic: requires-python
Dynamic: summary
